LICENSE
README.md
setup.py
qflash_jwt_package/__init__.py
qflash_jwt_package/authenticated_route.py
qflash_jwt_package/jwt.py
qflash_jwt_package.egg-info/PKG-INFO
qflash_jwt_package.egg-info/SOURCES.txt
qflash_jwt_package.egg-info/dependency_links.txt
qflash_jwt_package.egg-info/requires.txt
qflash_jwt_package.egg-info/top_level.txt