Metadata-Version: 2.1
Name: qflash-jwt-package
Version: 0.0.3
Summary: a small package for implement jwt security in API
Home-page: https://github.com/Quasar-Flash
Author: Marlon Martins
Author-email: marlon.martins@qflash.com.br
License: MIT License
Keywords: Package
Platform: UNKNOWN
License-File: LICENSE
